dp_chem/TUV.py
dp_chem/__init__.py
dp_chem/_fig_tools.py
dp_chem/binning.py
dp_chem/camxdata.py
dp_chem/correlation.py
dp_chem/diurnal.py
dp_chem/epa.py
dp_chem/gentools.py
dp_chem/gis.py
dp_chem/importer.py
dp_chem/molecule.py
dp_chem/odr.py
dp_chem/periodictable.py
dp_chem/reaction.py
dp_chem/reload.py
dp_chem/sigfig.py
dp_chem/stats.py
dp_chem/timeseries.py
dp_chem/uncertainvalue.py
dp_chem/units.py
dp_chem/weakacid.py
dp_chem-1.1.dist-info/LICENSE
dp_chem-1.1.dist-info/METADATA
dp_chem-1.1.dist-info/WHEEL
dp_chem-1.1.dist-info/top_level.txt
dp_chem-1.1.dist-info/RECORD
