Metadata-Version: 2.1
Name: dp-chem
Version: 1.1
Summary: A package for handling chemistry concepts and data
Author: Demetrios Pagonis
Author-email: demetriospagonis@weber.edu
License-File: LICENSE
Requires-Dist: numpy
Requires-Dist: pandas
Requires-Dist: jinja2
Requires-Dist: scipy
Requires-Dist: matplotlib
Requires-Dist: xarray
Requires-Dist: requests
Requires-Dist: cartopy
Requires-Dist: shapely
Requires-Dist: geopandas
